figures_package/__init__.py
figures_package/line_method.py
figures_package/point_method.py
figures_package/triangle_method.py
figures_pack-0.1.dist-info/METADATA
figures_pack-0.1.dist-info/WHEEL
figures_pack-0.1.dist-info/top_level.txt
figures_pack-0.1.dist-info/RECORD
