Metadata-Version: 2.1
Name: figures-pack
Version: 0.1
Summary: This  is very useful package
Home-page: UNKNOWN
Author: ToadHand
License: UNKNOWN
Platform: UNKNOWN
